LearningNashQLearning/__init__.py
LearningNashQLearning/main.py
LearningNashQLearning/Model/Agent.py
LearningNashQLearning/Model/Environment.py
LearningNashQLearning/Model/History.py
LearningNashQLearning/Model/NashQLearning.py
LearningNashQLearning/Model/__init__.py
LearningNashQLearning/View/EnvGraphDisplay.py
LearningNashQLearning/View/FinalDisplay.py
LearningNashQLearning/View/GameEditor.py
LearningNashQLearning/View/GraphClass.py
LearningNashQLearning/View/GridDisplay.py
LearningNashQLearning/View/NashQLearningWidgets.py
LearningNashQLearning/View/PresetGames.py
LearningNashQLearning/View/__init__.py
LearningNashQLearning-0.12.dist-info/METADATA
LearningNashQLearning-0.12.dist-info/WHEEL
LearningNashQLearning-0.12.dist-info/top_level.txt
LearningNashQLearning-0.12.dist-info/RECORD
