Metadata-Version: 2.1
Name: LearningNashQLearning
Version: 0.12
Summary: A simple NashQ-learning implementation in Python
Author: Paolo Ginefra, Federico Rocca, Andrea Tarabotto
Classifier: Programming Language :: Python :: 3
Classifier: License :: OSI Approved :: MIT License
Classifier: Operating System :: OS Independent
Requires-Python: >=3.9
Requires-Dist: numpy
Requires-Dist: matplotlib
Requires-Dist: seaborn
Requires-Dist: networkx
Requires-Dist: pygambit
Requires-Dist: netgraph
Requires-Dist: ipywidgets
Requires-Dist: notebook
Requires-Dist: ipympl
